withlog/.__init__.py.swp
withlog/.__init__.py.un~
withlog/.withlog.py.swp
withlog/.withlog.py.un~
withlog/__init__.py
withlog/__main__.py
withlog/withlog.py
withlog-0.0.3.dist-info/METADATA
withlog-0.0.3.dist-info/WHEEL
withlog-0.0.3.dist-info/RECORD
