Metadata-Version: 1.2
Name: withlog
Version: 0.0.3
Summary: A context manager to deal with logging level as context manager. 
Home-page: https://github.com/Carreau/withlog
License: UNKNOWN
Author: Matthias Bussonnier
Author-email: bussonniermatthias@gmail.com
Classifier: License :: OSI Approved :: MIT License
Requires-Dist: colorama
